<restlet scriptid="customscript_gw_rl_ap_integration_entry">
  <description></description>
  <isinactive>F</isinactive>
  <name>GW RL AP Integration Entry Point</name>
  <notifyadmins>F</notifyadmins>
  <notifyemails></notifyemails>
  <notifyowner>T</notifyowner>
  <notifyuser>F</notifyuser>
  <scriptfile>[/SuiteApps/com.gateweb.gwegui/gw_ap_doc/integration_api/gw_rl_ap_integration_entry_point.js]</scriptfile>
  <scriptdeployments>
    <scriptdeployment scriptid="customdeploy_gw_rl_ap_integration_entry">
      <allemployees>T</allemployees>
      <allpartners>F</allpartners>
      <allroles>T</allroles>
      <audslctrole></audslctrole>
      <isdeployed>T</isdeployed>
      <loglevel>DEBUG</loglevel>
      <status>RELEASED</status>
      <title>GW RL AP Integration Entry Point</title>
    </scriptdeployment>
  </scriptdeployments>
</restlet>